MosaBay/MosaBay.py
MosaBay/__init__.py
MosaBay/example.py
MosaBay-0.0.1.dist-info/METADATA
MosaBay-0.0.1.dist-info/WHEEL
MosaBay-0.0.1.dist-info/entry_points.txt
MosaBay-0.0.1.dist-info/top_level.txt
MosaBay-0.0.1.dist-info/RECORD
