Metadata-Version: 2.1
Name: MosaBay
Version: 0.0.1
Summary: MosaBayMosaBay
Author: DSA
Keywords: life-science
Platform: any
Classifier: Development Status :: 4 - Beta
Classifier: Intended Audience :: Developers
Classifier: Intended Audience :: Science/Research
Classifier: Topic :: Scientific/Engineering :: Bio-Informatics
Classifier: Programming Language :: Python :: 3
Classifier: Programming Language :: Python :: 3.8
Requires-Python: >=3.8
Requires-Dist: numpy (>=1.8)
